pgenlib.cpython-311-x86_64-linux-gnu.so
pgenlib-0.93.0.dist-info/METADATA
pgenlib-0.93.0.dist-info/WHEEL
pgenlib-0.93.0.dist-info/top_level.txt
pgenlib-0.93.0.dist-info/RECORD
pgenlib-0.93.0.dist-info/licenses/LICENSE
