Metadata-Version: 2.1
Name: Pgenlib
Version: 0.93.0
Summary: Python wrapper for pgenlib's basic reader and writer.
Home-page: https://github.com/chrchang/plink-ng
Author: Christopher Chang
Author-email: chrchang@alumni.caltech.edu
Project-URL: Bug Tracker, https://github.com/chrchang/plink-ng/issues
Classifier: Programming Language :: Python :: 3
Classifier: License :: OSI Approved :: GNU Lesser General Public License v3 (LGPLv3)
Classifier: Operating System :: OS Independent
Requires-Python: >=3.9
License-File: LICENSE
Requires-Dist: numpy>=1.19.3
